lzdeb/__init__.py
lzdeb/lzdeb.py
lzdeb/utils.py
lzdeb-0.1.3.1.data/scripts/lzdeb
lzdeb-0.1.3.1.dist-info/LICENSE
lzdeb-0.1.3.1.dist-info/METADATA
lzdeb-0.1.3.1.dist-info/WHEEL
lzdeb-0.1.3.1.dist-info/top_level.txt
lzdeb-0.1.3.1.dist-info/RECORD
