Metadata-Version: 2.1
Name: lzdeb
Version: 0.1.3.1
Summary: LzDeb - Build debian packages the lazy way
Home-page: https://github.com/mkjt2/lzdeb
Author: Jackie Tung
Author-email: jackie.tung@gmail.com
License: UNKNOWN
Platform: UNKNOWN
Classifier: License :: OSI Approved :: MIT License
Classifier: Operating System :: POSIX :: Linux
Classifier: Operating System :: MacOS :: MacOS X
Classifier: Programming Language :: Python :: 3
Requires-Dist: PyYAML
Requires-Dist: docker
